logicalprograms/DigitSum.py
logicalprograms/IntegerToRoman.py
logicalprograms/Number_To_Word.py
logicalprograms/__init__.py
logicalprograms-0.1.dist-info/LICENSE.txt
logicalprograms-0.1.dist-info/METADATA
logicalprograms-0.1.dist-info/WHEEL
logicalprograms-0.1.dist-info/top_level.txt
logicalprograms-0.1.dist-info/RECORD
